datetime_extractor/TimestampExtractor.py
datetime_extractor/__init__.py
datetime_extractor-0.1.dist-info/METADATA
datetime_extractor-0.1.dist-info/WHEEL
datetime_extractor-0.1.dist-info/top_level.txt
datetime_extractor-0.1.dist-info/RECORD
