Metadata-Version: 2.1
Name: datetime-extractor
Version: 0.1
Summary: Extracts timestamp from a given text/string using this package
Home-page: https://github.com/ydineshy225/datetime_extractor
Author: Yeddu Dinesh Babu
Author-email: ydineshy225@gmail.com
License: UNKNOWN
Platform: UNKNOWN
Classifier: Programming Language :: Python :: 3
Classifier: License :: OSI Approved :: MIT License
Classifier: Operating System :: OS Independent
